infocyteapiquery/__init__.py
infocyteapiquery/infocyteapiquery.py
infocyteapiquery-1.1.16.dist-info/AUTHORS.md
infocyteapiquery-1.1.16.dist-info/LICENSE
infocyteapiquery-1.1.16.dist-info/METADATA
infocyteapiquery-1.1.16.dist-info/WHEEL
infocyteapiquery-1.1.16.dist-info/top_level.txt
infocyteapiquery-1.1.16.dist-info/RECORD
