Metadata-Version: 2.1
Name: infocyteapiquery
Version: 1.1.16
Summary: Used to get API data from Infocyte Cloud Instances into the pandas DataFrame
Home-page: https://github.com/manjesh23/infocyteapiquery
Author: Manjesh N
Author-email: manjesh_n@hotmail.com
License: Apache Software License 2.0
Keywords: infocyteapiquery,infocyte
Platform: UNKNOWN
Classifier: Development Status :: 5 - Production/Stable
Classifier: Intended Audience :: Developers
Classifier: Intended Audience :: End Users/Desktop
Classifier: Intended Audience :: Information Technology
Classifier: Intended Audience :: Customer Service
Classifier: License :: OSI Approved :: Apache Software License
Classifier: Natural Language :: English
Classifier: Programming Language :: Python :: 3.7
Classifier: Programming Language :: Python :: 3.8
Classifier: Programming Language :: Python :: 3.9
Requires-Python: >=3.7
License-File: LICENSE
License-File: AUTHORS.md
Requires-Dist: requests
Requires-Dist: pandas
Requires-Dist: tqdm
Requires-Dist: paginateit
